{
  "slug": "bayers",
  "nom": "Bayers",
  "fetchedAt": "2026-03-15T19:24:28.302Z",
  "header": [
    {
      "url": "https://upload.wikimedia.org/wikipedia/commons/f/f1/Bayers_ch1.JPG",
      "sourceUrl": "https://commons.wikimedia.org/wiki/File%3ABayers%20ch1.JPG",
      "title": "Bayers ch1.JPG",
      "description": "château de Bayers, Charente, France",
      "width": 1600,
      "height": 1200,
      "size": 259250,
      "timestamp": "2010-10-10T08:31:51Z",
      "author": "Jack ma",
      "license": "CC BY-SA 3.0",
      "licenseUrl": "https://creativecommons.org/licenses/",
      "score": 7
    }
  ],
  "lieux": [
    {
      "label": "Château de Bayers",
      "photos": []
    },
    {
      "label": "Église Saint-Sulpice",
      "photos": [
        {
          "url": "https://upload.wikimedia.org/wikipedia/commons/7/7a/Bayers_eg1.JPG",
          "sourceUrl": "https://commons.wikimedia.org/wiki/File%3ABayers%20eg1.JPG",
          "title": "Bayers eg1.JPG",
          "description": "église de Bayers, Charente, France",
          "width": 1600,
          "height": 1200,
          "size": 282166,
          "timestamp": "2010-10-10T08:34:01Z",
          "author": "Jack ma",
          "license": "CC BY-SA 3.0",
          "licenseUrl": "https://creativecommons.org/licenses/",
          "score": 5
        }
      ]
    },
    {
      "label": "Lavoir de Bayers",
      "photos": []
    }
  ]
}