{
  "slug": "migennes",
  "nom": "Migennes",
  "fetchedAt": "2026-03-16T21:35:03.684Z",
  "header": [
    {
      "url": "https://upload.wikimedia.org/wikipedia/commons/2/21/Migennes_-_le_canal_et_le_dos_de_la_gare.jpg",
      "sourceUrl": "https://commons.wikimedia.org/wiki/File%3AMigennes%20-%20le%20canal%20et%20le%20dos%20de%20la%20gare.jpg",
      "title": "Migennes - le canal et le dos de la gare.jpg",
      "description": "Migennes - le canal et le dos de la gare",
      "width": 3264,
      "height": 2448,
      "size": 2439526,
      "timestamp": "2022-08-08T22:45:50Z",
      "author": "AirScott",
      "license": "CC BY-SA 4.0",
      "licenseUrl": "https://creativecommons.org/licenses/",
      "score": 7
    },
    {
      "url": "https://upload.wikimedia.org/wikipedia/commons/4/4d/Migennes_-_Canal.jpg",
      "sourceUrl": "https://commons.wikimedia.org/wiki/File%3AMigennes%20-%20Canal.jpg",
      "title": "Migennes - Canal.jpg",
      "description": "Migennes - Canal",
      "width": 3264,
      "height": 2448,
      "size": 2989815,
      "timestamp": "2022-08-08T22:45:50Z",
      "author": "AirScott",
      "license": "CC BY-SA 4.0",
      "licenseUrl": "https://creativecommons.org/licenses/",
      "score": 7
    },
    {
      "url": "https://upload.wikimedia.org/wikipedia/commons/0/05/Migennes_-_quai_dans_la_gare.jpg",
      "sourceUrl": "https://commons.wikimedia.org/wiki/File%3AMigennes%20-%20quai%20dans%20la%20gare.jpg",
      "title": "Migennes - quai dans la gare.jpg",
      "description": "Migennes - quai dans la gare",
      "width": 3264,
      "height": 2448,
      "size": 2521298,
      "timestamp": "2022-08-08T22:51:09Z",
      "author": "AirScott",
      "license": "CC BY-SA 4.0",
      "licenseUrl": "https://creativecommons.org/licenses/",
      "score": 7
    }
  ],
  "lieux": [
    {
      "label": "Port de plaisance de Migennes",
      "photos": [
        {
          "url": "https://upload.wikimedia.org/wikipedia/commons/9/9b/Rue_du_port_des_fontaines_%C3%A0_Bonnard._Tron%C3%A7on_en_voie_partag%C3%A9e_de_la_v%C3%A9loroute_de_Migennes_%C3%A0_Auxerre.jpg",
          "sourceUrl": "https://commons.wikimedia.org/wiki/File%3ARue%20du%20port%20des%20fontaines%20%C3%A0%20Bonnard.%20Tron%C3%A7on%20en%20voie%20partag%C3%A9e%20de%20la%20v%C3%A9loroute%20de%20Migennes%20%C3%A0%20Auxerre.jpg",
          "title": "Rue du port des fontaines à Bonnard. Tronçon en voie partagée de la véloroute de Migennes à Auxerre.jpg",
          "description": "Rue du port des fontaines à Bonnard. Tronçon en voie partagée de la véloroute de Migennes à Auxerre",
          "width": 5184,
          "height": 3888,
          "size": 4570189,
          "timestamp": "2025-10-26T07:54:10Z",
          "author": "VVVCFFrance",
          "license": "CC0",
          "licenseUrl": "https://creativecommons.org/licenses/",
          "score": 7
        },
        {
          "url": "https://upload.wikimedia.org/wikipedia/commons/e/e9/Rue_du_port_des_fontaines_%C3%A0_Bonnard._Voie_partag%C3%A9e_sur_la_v%C3%A9loroute_de_Migennes_%C3%A0_Auxerre.jpg",
          "sourceUrl": "https://commons.wikimedia.org/wiki/File%3ARue%20du%20port%20des%20fontaines%20%C3%A0%20Bonnard.%20Voie%20partag%C3%A9e%20sur%20la%20v%C3%A9loroute%20de%20Migennes%20%C3%A0%20Auxerre.jpg",
          "title": "Rue du port des fontaines à Bonnard. Voie partagée sur la véloroute de Migennes à Auxerre.jpg",
          "description": "Rue du port  des fontaines à Bonnard. Voie partagée sur la véloroute de Migennes à Auxerre",
          "width": 1131,
          "height": 904,
          "size": 202795,
          "timestamp": "2025-10-26T07:58:11Z",
          "author": "VVVCFFrance",
          "license": "CC0",
          "licenseUrl": "https://creativecommons.org/licenses/",
          "score": 6
        },
        {
          "url": "https://upload.wikimedia.org/wikipedia/commons/2/2b/Migennes_-_Port_de_plaisance.jpg",
          "sourceUrl": "https://commons.wikimedia.org/wiki/File%3AMigennes%20-%20Port%20de%20plaisance.jpg",
          "title": "Migennes - Port de plaisance.jpg",
          "description": "The port of Migennes, Yonne, France.",
          "width": 2048,
          "height": 1536,
          "size": 576176,
          "timestamp": "2010-09-06T10:29:07Z",
          "author": "Benjism89",
          "license": "CC BY-SA 3.0",
          "licenseUrl": "https://creativecommons.org/licenses/",
          "score": 5
        }
      ]
    },
    {
      "label": "Église Saint-Pancrace",
      "photos": [
        {
          "url": "https://upload.wikimedia.org/wikipedia/commons/1/19/%C3%89glise_Saint-Pancrace_de_Migennes.jpg",
          "sourceUrl": "https://commons.wikimedia.org/wiki/File%3A%C3%89glise%20Saint-Pancrace%20de%20Migennes.jpg",
          "title": "Église Saint-Pancrace de Migennes.jpg",
          "description": "Église Saint-Pancrace de Migennes",
          "width": 6000,
          "height": 4000,
          "size": 9083181,
          "timestamp": "2020-09-30T21:54:03Z",
          "author": "Baidax",
          "license": "CC BY-SA 4.0",
          "licenseUrl": "https://creativecommons.org/licenses/",
          "score": 7
        },
        {
          "url": "https://upload.wikimedia.org/wikipedia/commons/6/66/%C3%89glise_Saint-Pancrace_de_Migennes_%282%29.jpg",
          "sourceUrl": "https://commons.wikimedia.org/wiki/File%3A%C3%89glise%20Saint-Pancrace%20de%20Migennes%20(2).jpg",
          "title": "Église Saint-Pancrace de Migennes (2).jpg",
          "description": "Église Saint-Pancrace de Migennes",
          "width": 6000,
          "height": 4000,
          "size": 9713341,
          "timestamp": "2020-09-30T21:54:03Z",
          "author": "Baidax",
          "license": "CC BY-SA 4.0",
          "licenseUrl": "https://creativecommons.org/licenses/",
          "score": 7
        },
        {
          "url": "https://upload.wikimedia.org/wikipedia/commons/b/b2/L%27%C3%A9glise_du_Vieux-Migennes.jpg",
          "sourceUrl": "https://commons.wikimedia.org/wiki/File%3AL'%C3%A9glise%20du%20Vieux-Migennes.jpg",
          "title": "L'église du Vieux-Migennes.jpg",
          "description": "L'église du Vieux-Migennes",
          "width": 2835,
          "height": 1890,
          "size": 2782443,
          "timestamp": "2017-04-25T15:35:39Z",
          "author": "Pierre Lapointe",
          "license": "CC BY-SA 4.0",
          "licenseUrl": "https://creativecommons.org/licenses/",
          "score": 6
        }
      ]
    },
    {
      "label": "Gare de Laroche-Migennes",
      "photos": [
        {
          "url": "https://upload.wikimedia.org/wikipedia/commons/3/3c/Crible_m%C3%A9canique_%C3%A0_combustibles_du_d%C3%A9p%C3%B4t_de_Laroche_-_Vue_du_crible_%28Photo_Georgeon%2C_Migennes%2C_Bulletin_PLM_n%C2%B07_de_janvier_1930%29.jpg",
          "sourceUrl": "https://commons.wikimedia.org/wiki/File%3ACrible%20m%C3%A9canique%20%C3%A0%20combustibles%20du%20d%C3%A9p%C3%B4t%20de%20Laroche%20-%20Vue%20du%20crible%20(Photo%20Georgeon%2C%20Migennes%2C%20Bulletin%20PLM%20n%C2%B07%20de%20janvier%201930).jpg",
          "title": "Crible mécanique à combustibles du dépôt de Laroche - Vue du crible (Photo Georgeon, Migennes, Bulletin PLM n°7 de janvier 1930).jpg",
          "description": "Crible mécanique à combustibles du dépôt de Laroche - Vue du crible (Photo Georgeon, Migennes) - Le charbon criblé est reçu dans des wagonnets Decauville à voies de 0,50 m, lesquels sont acheminés rapidement au lieu de déversement dans les tenders (Bulletin PLM n°7 de janvier 1930)",
          "width": 1297,
          "height": 981,
          "size": 184979,
          "timestamp": "2020-08-26T02:28:30Z",
          "author": "Photo Georgeon, Migennes",
          "license": "Public domain",
          "licenseUrl": "https://creativecommons.org/licenses/",
          "score": 8
        },
        {
          "url": "https://upload.wikimedia.org/wikipedia/commons/9/97/753000_-_Ligne_de_Laroche-Migennes_%C3%A0_Cosne.png",
          "sourceUrl": "https://commons.wikimedia.org/wiki/File%3A753000%20-%20Ligne%20de%20Laroche-Migennes%20%C3%A0%20Cosne.png",
          "title": "753000 - Ligne de Laroche-Migennes à Cosne.png",
          "description": "Tracé de la ligne ferroviaire française de Laroche-Migennes à Cosne",
          "width": 3507,
          "height": 2480,
          "size": 757723,
          "timestamp": "2023-06-19T13:54:04Z",
          "author": "Poudou99",
          "license": "CC BY 4.0",
          "licenseUrl": "https://creativecommons.org/licenses/",
          "score": 7
        },
        {
          "url": "https://upload.wikimedia.org/wikipedia/commons/2/21/Migennes_-_le_canal_et_le_dos_de_la_gare.jpg",
          "sourceUrl": "https://commons.wikimedia.org/wiki/File%3AMigennes%20-%20le%20canal%20et%20le%20dos%20de%20la%20gare.jpg",
          "title": "Migennes - le canal et le dos de la gare.jpg",
          "description": "Migennes - le canal et le dos de la gare",
          "width": 3264,
          "height": 2448,
          "size": 2439526,
          "timestamp": "2022-08-08T22:45:50Z",
          "author": "AirScott",
          "license": "CC BY-SA 4.0",
          "licenseUrl": "https://creativecommons.org/licenses/",
          "score": 7
        }
      ]
    }
  ]
}