{
  "slug": "belley",
  "nom": "Belley",
  "fetchedAt": "2026-03-13T00:15:58.567Z",
  "header": [
    {
      "url": "https://upload.wikimedia.org/wikipedia/commons/2/20/Fontaine_Place_Terreaux_-_Belley_%28FR01%29_-_2022-06-12_-_1.jpg",
      "sourceUrl": "https://commons.wikimedia.org/wiki/File%3AFontaine%20Place%20Terreaux%20-%20Belley%20(FR01)%20-%202022-06-12%20-%201.jpg",
      "title": "Fontaine Place Terreaux - Belley (FR01) - 2022-06-12 - 1.jpg",
      "width": 4032,
      "height": 3024,
      "size": 5367093,
      "timestamp": "2022-06-13T15:50:20Z",
      "author": "Chabe01",
      "license": "CC BY-SA 4.0",
      "licenseUrl": "https://creativecommons.org/licenses/",
      "score": 7
    },
    {
      "url": "https://upload.wikimedia.org/wikipedia/commons/7/7b/Fontaine_Place_Terreaux_-_Belley_%28FR01%29_-_2022-06-12_-_2.jpg",
      "sourceUrl": "https://commons.wikimedia.org/wiki/File%3AFontaine%20Place%20Terreaux%20-%20Belley%20(FR01)%20-%202022-06-12%20-%202.jpg",
      "title": "Fontaine Place Terreaux - Belley (FR01) - 2022-06-12 - 2.jpg",
      "width": 4032,
      "height": 3024,
      "size": 2827870,
      "timestamp": "2022-06-13T15:50:27Z",
      "author": "Chabe01",
      "license": "CC BY-SA 4.0",
      "licenseUrl": "https://creativecommons.org/licenses/",
      "score": 7
    },
    {
      "url": "https://upload.wikimedia.org/wikipedia/commons/7/7a/Salle_F%C3%AAtes_-_Belley_%28FR01%29_-_2022-06-12_-_2.jpg",
      "sourceUrl": "https://commons.wikimedia.org/wiki/File%3ASalle%20F%C3%AAtes%20-%20Belley%20(FR01)%20-%202022-06-12%20-%202.jpg",
      "title": "Salle Fêtes - Belley (FR01) - 2022-06-12 - 2.jpg",
      "width": 5966,
      "height": 4064,
      "size": 21294255,
      "timestamp": "2022-06-13T15:56:39Z",
      "author": "Chabe01",
      "license": "CC BY-SA 4.0",
      "licenseUrl": "https://creativecommons.org/licenses/",
      "score": 7
    }
  ],
  "lieux": [
    {
      "label": "Cathédrale Saint-Jean-Baptiste",
      "photos": [
        {
          "url": "https://upload.wikimedia.org/wikipedia/commons/b/b8/Cath%C3%A9drale_Saint_Jean_-_Belley_%28FR01%29_-_2022-06-12_-_9.jpg",
          "sourceUrl": "https://commons.wikimedia.org/wiki/File%3ACath%C3%A9drale%20Saint%20Jean%20-%20Belley%20(FR01)%20-%202022-06-12%20-%209.jpg",
          "title": "Cathédrale Saint Jean - Belley (FR01) - 2022-06-12 - 9.jpg",
          "width": 4032,
          "height": 3024,
          "size": 4206989,
          "timestamp": "2022-06-13T15:50:11Z",
          "author": "Chabe01",
          "license": "CC BY-SA 4.0",
          "licenseUrl": "https://creativecommons.org/licenses/",
          "score": 7
        },
        {
          "url": "https://upload.wikimedia.org/wikipedia/commons/0/04/Cath%C3%A9drale_Saint_Jean_-_Belley_%28FR01%29_-_2022-06-12_-_10.jpg",
          "sourceUrl": "https://commons.wikimedia.org/wiki/File%3ACath%C3%A9drale%20Saint%20Jean%20-%20Belley%20(FR01)%20-%202022-06-12%20-%2010.jpg",
          "title": "Cathédrale Saint Jean - Belley (FR01) - 2022-06-12 - 10.jpg",
          "width": 4032,
          "height": 3024,
          "size": 3860064,
          "timestamp": "2022-06-13T15:50:12Z",
          "author": "Chabe01",
          "license": "CC BY-SA 4.0",
          "licenseUrl": "https://creativecommons.org/licenses/",
          "score": 7
        },
        {
          "url": "https://upload.wikimedia.org/wikipedia/commons/e/e4/La_cath%C3%A9drale_de_Belley_en_travaux_en_septembre_2019%2C_photographi%C3%A9e_depuis_la_cour_du_palais_%C3%A9piscopal_%28%C3%A0_gauche%29.jpg",
          "sourceUrl": "https://commons.wikimedia.org/wiki/File%3ALa%20cath%C3%A9drale%20de%20Belley%20en%20travaux%20en%20septembre%202019%2C%20photographi%C3%A9e%20depuis%20la%20cour%20du%20palais%20%C3%A9piscopal%20(%C3%A0%20gauche).jpg",
          "title": "La cathédrale de Belley en travaux en septembre 2019, photographiée depuis la cour du palais épiscopal (à gauche).jpg",
          "width": 4032,
          "height": 3024,
          "size": 6581773,
          "timestamp": "2019-09-15T13:04:05Z",
          "author": "<bdi><a href=\"https://www.wikidata.org/wiki/Q42790984\" class=\"extiw\" title=\"d:Q42790984\"><span title=\"French computing engineer\">Benoît Prieur</span></a></bdi>",
          "license": "CC0",
          "licenseUrl": "https://creativecommons.org/licenses/",
          "score": 6
        }
      ]
    },
    {
      "label": "Palais épiscopal de Belley",
      "photos": [
        {
          "url": "https://upload.wikimedia.org/wikipedia/commons/a/a3/Palais_%C3%89piscopal_-_Belley_%28FR01%29_-_2022-06-12_-_1.jpg",
          "sourceUrl": "https://commons.wikimedia.org/wiki/File%3APalais%20%C3%89piscopal%20-%20Belley%20(FR01)%20-%202022-06-12%20-%201.jpg",
          "title": "Palais Épiscopal - Belley (FR01) - 2022-06-12 - 1.jpg",
          "width": 4032,
          "height": 3024,
          "size": 4872747,
          "timestamp": "2022-06-13T15:56:50Z",
          "author": "Chabe01",
          "license": "CC BY-SA 4.0",
          "licenseUrl": "https://creativecommons.org/licenses/",
          "score": 7
        },
        {
          "url": "https://upload.wikimedia.org/wikipedia/commons/7/74/Palais_%C3%89piscopal_-_Belley_%28FR01%29_-_2022-06-12_-_2.jpg",
          "sourceUrl": "https://commons.wikimedia.org/wiki/File%3APalais%20%C3%89piscopal%20-%20Belley%20(FR01)%20-%202022-06-12%20-%202.jpg",
          "title": "Palais Épiscopal - Belley (FR01) - 2022-06-12 - 2.jpg",
          "width": 4032,
          "height": 3024,
          "size": 4152540,
          "timestamp": "2022-06-13T15:56:50Z",
          "author": "Chabe01",
          "license": "CC BY-SA 4.0",
          "licenseUrl": "https://creativecommons.org/licenses/",
          "score": 7
        },
        {
          "url": "https://upload.wikimedia.org/wikipedia/commons/3/33/Palais_%C3%89piscopal_-_Belley_%28FR01%29_-_2022-06-12_-_3.jpg",
          "sourceUrl": "https://commons.wikimedia.org/wiki/File%3APalais%20%C3%89piscopal%20-%20Belley%20(FR01)%20-%202022-06-12%20-%203.jpg",
          "title": "Palais Épiscopal - Belley (FR01) - 2022-06-12 - 3.jpg",
          "width": 4032,
          "height": 3024,
          "size": 4969982,
          "timestamp": "2022-06-13T15:56:51Z",
          "author": "Chabe01",
          "license": "CC BY-SA 4.0",
          "licenseUrl": "https://creativecommons.org/licenses/",
          "score": 7
        }
      ]
    },
    {
      "label": "Promenade des Barattes",
      "photos": []
    },
    {
      "label": "Jardin du Clos Landar",
      "photos": []
    }
  ]
}