{
  "slug": "eglise-notre-dame-de-l-assomption-de-longpont-sur-orge",
  "nom": "eglise notre dame de l assomption de longpont sur orge",
  "fetchedAt": "2026-03-16T12:56:55.166Z",
  "header": [],
  "lieux": [
    {
      "label": "Portail ouest sculpté",
      "photos": []
    },
    {
      "label": "Nef et voûte en berceau brisé",
      "photos": []
    },
    {
      "label": "Chœur et chevet",
      "photos": []
    },
    {
      "label": "Tour-clocher vue depuis le parvis",
      "photos": []
    }
  ]
}