{
  "slug": "saint-amand-de-coly",
  "nom": "Saint-Amand-de-Coly",
  "fetchedAt": "2026-03-14T11:55:34.648Z",
  "header": [
    {
      "url": "https://upload.wikimedia.org/wikipedia/commons/f/f9/NRA_ZO_Saint-Amand-de-Coly_9V2_24.jpg",
      "sourceUrl": "https://commons.wikimedia.org/wiki/File%3ANRA%20ZO%20Saint-Amand-de-Coly%209V2%2024.jpg",
      "title": "NRA ZO Saint-Amand-de-Coly 9V2 24.jpg",
      "width": 4032,
      "height": 2268,
      "size": 5550093,
      "timestamp": "2022-11-11T15:41:52Z",
      "author": "Pastèque24",
      "license": "CC BY-SA 4.0",
      "licenseUrl": "https://creativecommons.org/licenses/",
      "score": 7
    },
    {
      "url": "https://upload.wikimedia.org/wikipedia/commons/2/20/F07.St.-Amand.0052.JPG",
      "sourceUrl": "https://commons.wikimedia.org/wiki/File%3AF07.St.-Amand.0052.JPG",
      "title": "F07.St.-Amand.0052.JPG",
      "width": 3872,
      "height": 2592,
      "size": 2393975,
      "timestamp": "2010-12-15T07:30:08Z",
      "author": "Jochen Jahnke",
      "license": "CC BY-SA 3.0",
      "licenseUrl": "https://creativecommons.org/licenses/",
      "score": 5
    },
    {
      "url": "https://upload.wikimedia.org/wikipedia/commons/c/ce/Saint-Amand-de-Coly_-_Mairie_01.JPG",
      "sourceUrl": "https://commons.wikimedia.org/wiki/File%3ASaint-Amand-de-Coly%20-%20Mairie%2001.JPG",
      "title": "Saint-Amand-de-Coly - Mairie 01.JPG",
      "width": 3840,
      "height": 2560,
      "size": 4843895,
      "timestamp": "2013-08-07T16:06:27Z",
      "author": "Pymouss",
      "license": "CC BY-SA 3.0",
      "licenseUrl": "https://creativecommons.org/licenses/",
      "score": 5
    }
  ],
  "lieux": [
    {
      "label": "Abbatiale Saint-Amand-de-Coly",
      "photos": [
        {
          "url": "https://upload.wikimedia.org/wikipedia/commons/e/e1/Saint-Amand-de-Coly_%C3%A9glise_chapelle_nord_peintures.jpg",
          "sourceUrl": "https://commons.wikimedia.org/wiki/File%3ASaint-Amand-de-Coly%20%C3%A9glise%20chapelle%20nord%20peintures.jpg",
          "title": "Saint-Amand-de-Coly église chapelle nord peintures.jpg",
          "width": 3124,
          "height": 2343,
          "size": 1544318,
          "timestamp": "2018-12-11T17:16:31Z",
          "author": "Père Igor",
          "license": "CC BY-SA 4.0",
          "licenseUrl": "https://creativecommons.org/licenses/",
          "score": 6
        },
        {
          "url": "https://upload.wikimedia.org/wikipedia/commons/0/08/Saint-Amand-de-Coly_%C3%A9glise_chapelle_sud_niche.jpg",
          "sourceUrl": "https://commons.wikimedia.org/wiki/File%3ASaint-Amand-de-Coly%20%C3%A9glise%20chapelle%20sud%20niche.jpg",
          "title": "Saint-Amand-de-Coly église chapelle sud niche.jpg",
          "width": 3190,
          "height": 2393,
          "size": 1448283,
          "timestamp": "2018-12-11T17:18:50Z",
          "author": "Père Igor",
          "license": "CC BY-SA 4.0",
          "licenseUrl": "https://creativecommons.org/licenses/",
          "score": 6
        },
        {
          "url": "https://upload.wikimedia.org/wikipedia/commons/8/8b/Saint-Amand-de-Coly_%C3%A9glise_choeur_plafond.jpg",
          "sourceUrl": "https://commons.wikimedia.org/wiki/File%3ASaint-Amand-de-Coly%20%C3%A9glise%20choeur%20plafond.jpg",
          "title": "Saint-Amand-de-Coly église choeur plafond.jpg",
          "width": 3264,
          "height": 2448,
          "size": 1515466,
          "timestamp": "2018-12-11T17:22:58Z",
          "author": "Père Igor",
          "license": "CC BY-SA 4.0",
          "licenseUrl": "https://creativecommons.org/licenses/",
          "score": 6
        }
      ]
    },
    {
      "label": "Lavoir ancien",
      "photos": []
    },
    {
      "label": "Fontaine Saint-Amand",
      "photos": [
        {
          "url": "https://upload.wikimedia.org/wikipedia/commons/7/7d/Saint-Amand-de-Coly_lavoir_%286%29.jpg",
          "sourceUrl": "https://commons.wikimedia.org/wiki/File%3ASaint-Amand-de-Coly%20lavoir%20(6).jpg",
          "title": "Saint-Amand-de-Coly lavoir (6).jpg",
          "width": 3264,
          "height": 2448,
          "size": 3341862,
          "timestamp": "2018-12-09T18:36:43Z",
          "author": "Père Igor",
          "license": "CC BY-SA 4.0",
          "licenseUrl": "https://creativecommons.org/licenses/",
          "score": 6
        }
      ]
    },
    {
      "label": "Vue depuis le cimetière",
      "photos": []
    }
  ]
}