{
  "slug": "plage-de-la-couronne",
  "nom": "Plage de la Couronne",
  "fetchedAt": "2026-03-17T22:59:37.733Z",
  "header": [
    {
      "url": "https://upload.wikimedia.org/wikipedia/commons/e/e1/Gare_de_La_Couronne_Carro_%28Novembre_2021%29_depuis_le_quai_direction_Marseille.jpg",
      "sourceUrl": "https://commons.wikimedia.org/wiki/File%3AGare%20de%20La%20Couronne%20Carro%20(Novembre%202021)%20depuis%20le%20quai%20direction%20Marseille.jpg",
      "title": "Gare de La Couronne Carro (Novembre 2021) depuis le quai direction Marseille.jpg",
      "description": "Gare de La Couronne Carro (Novembre 2021) depuis le quai direction Marseille",
      "width": 4608,
      "height": 3456,
      "size": 3968390,
      "timestamp": "2021-11-15T11:34:41Z",
      "author": "Teolemon",
      "license": "CC BY-SA 4.0",
      "licenseUrl": "https://creativecommons.org/licenses/",
      "score": 7
    },
    {
      "url": "https://upload.wikimedia.org/wikipedia/commons/b/bf/Gare_de_La_Couronne_Carro_%28Novembre_2021%29_depuis_le_quai_direction_Miramas.jpg",
      "sourceUrl": "https://commons.wikimedia.org/wiki/File%3AGare%20de%20La%20Couronne%20Carro%20(Novembre%202021)%20depuis%20le%20quai%20direction%20Miramas.jpg",
      "title": "Gare de La Couronne Carro (Novembre 2021) depuis le quai direction Miramas.jpg",
      "description": "Gare de La Couronne Carro (Novembre 2021) depuis le quai direction Miramas",
      "width": 4032,
      "height": 3024,
      "size": 3285874,
      "timestamp": "2021-11-15T11:34:41Z",
      "author": "Teolemon",
      "license": "CC BY-SA 4.0",
      "licenseUrl": "https://creativecommons.org/licenses/",
      "score": 7
    },
    {
      "url": "https://upload.wikimedia.org/wikipedia/commons/2/27/Gare_de_La_Couronne_Carro_%28Novembre_2021%29.jpg",
      "sourceUrl": "https://commons.wikimedia.org/wiki/File%3AGare%20de%20La%20Couronne%20Carro%20(Novembre%202021).jpg",
      "title": "Gare de La Couronne Carro (Novembre 2021).jpg",
      "description": "Gare de La Couronne Carro (Novembre 2021)",
      "width": 4032,
      "height": 3024,
      "size": 3578686,
      "timestamp": "2021-11-15T11:34:41Z",
      "author": "Teolemon",
      "license": "CC BY-SA 4.0",
      "licenseUrl": "https://creativecommons.org/licenses/",
      "score": 7
    }
  ],
  "lieux": [
    {
      "label": "Digue de la Couronne",
      "photos": []
    },
    {
      "label": "Sentier piéton sous les pins",
      "photos": []
    }
  ]
}