{
  "slug": "souvigny",
  "nom": "Souvigny",
  "fetchedAt": "2026-03-18T19:50:15.224Z",
  "header": [
    {
      "url": "https://upload.wikimedia.org/wikipedia/commons/f/f6/Prieur%C3%A9_b%C3%A9n%C3%A9dictin_de_Souvigny-Vue_du_chemin_de_Saint_Jacques-20151026.jpg",
      "sourceUrl": "https://commons.wikimedia.org/wiki/File%3APrieur%C3%A9%20b%C3%A9n%C3%A9dictin%20de%20Souvigny-Vue%20du%20chemin%20de%20Saint%20Jacques-20151026.jpg",
      "title": "Prieuré bénédictin de Souvigny-Vue du chemin de Saint Jacques-20151026.jpg",
      "description": "View of the Priory St. Peter and St. Paul at the  exit of the Way of St. James, Aristide Briand square - (Waymarks near the fountain for pilgrims, far left).",
      "width": 5472,
      "height": 3648,
      "size": 7920319,
      "timestamp": "2015-10-29T08:47:56Z",
      "author": "Daniel VILLAFRUELA",
      "license": "CC BY-SA 4.0",
      "licenseUrl": "https://creativecommons.org/licenses/",
      "score": 8
    },
    {
      "url": "https://upload.wikimedia.org/wikipedia/commons/b/ba/Souvigny_%28www.xtof.photo%29.jpg",
      "sourceUrl": "https://commons.wikimedia.org/wiki/File%3ASouvigny%20(www.xtof.photo).jpg",
      "title": "Souvigny (www.xtof.photo).jpg",
      "description": "This is a panoramic view of Souvigny, including its medieval priory, the garden and the main square, from the sky.",
      "width": 2961,
      "height": 1440,
      "size": 1818796,
      "timestamp": "2019-08-15T16:18:23Z",
      "author": "Christophe Meneboeuf",
      "license": "CC BY-SA 4.0",
      "licenseUrl": "https://creativecommons.org/licenses/",
      "score": 8
    },
    {
      "url": "https://upload.wikimedia.org/wikipedia/commons/d/d2/Souvigny-%C3%89glise_Saint_Marc-20151026.jpg",
      "sourceUrl": "https://commons.wikimedia.org/wiki/File%3ASouvigny-%C3%89glise%20Saint%20Marc-20151026.jpg",
      "title": "Souvigny-Église Saint Marc-20151026.jpg",
      "description": "Former parish church St. Mark, 12th century.",
      "width": 5400,
      "height": 3600,
      "size": 6302541,
      "timestamp": "2015-10-28T08:55:51Z",
      "author": "Daniel VILLAFRUELA",
      "license": "CC BY-SA 4.0",
      "licenseUrl": "https://creativecommons.org/licenses/",
      "score": 6
    }
  ],
  "lieux": [
    {
      "label": "Prieurale Saint-Pierre-et-Saint-Paul",
      "photos": [
        {
          "url": "https://upload.wikimedia.org/wikipedia/commons/8/8e/%C3%89glise_prieurale_de_Souvigny-Chapiteaux_%28a%29-20151026.jpg",
          "sourceUrl": "https://commons.wikimedia.org/wiki/File%3A%C3%89glise%20prieurale%20de%20Souvigny-Chapiteaux%20(a)-20151026.jpg",
          "title": "Église prieurale de Souvigny-Chapiteaux (a)-20151026.jpg",
          "description": "Capital of the Northern aisle.",
          "width": 5472,
          "height": 3648,
          "size": 9971767,
          "timestamp": "2015-11-01T06:09:27Z",
          "author": "Daniel VILLAFRUELA",
          "license": "CC BY-SA 4.0",
          "licenseUrl": "https://creativecommons.org/licenses/",
          "score": 6
        },
        {
          "url": "https://upload.wikimedia.org/wikipedia/commons/7/7c/%C3%89glise_prieurale_de_Souvigny-Chapiteaux_%28b%29-20151026.jpg",
          "sourceUrl": "https://commons.wikimedia.org/wiki/File%3A%C3%89glise%20prieurale%20de%20Souvigny-Chapiteaux%20(b)-20151026.jpg",
          "title": "Église prieurale de Souvigny-Chapiteaux (b)-20151026.jpg",
          "description": "Capital of the Northern aisle.",
          "width": 5472,
          "height": 3648,
          "size": 8537625,
          "timestamp": "2015-11-01T06:26:54Z",
          "author": "Daniel VILLAFRUELA",
          "license": "CC BY-SA 4.0",
          "licenseUrl": "https://creativecommons.org/licenses/",
          "score": 6
        },
        {
          "url": "https://upload.wikimedia.org/wikipedia/commons/1/1c/%C3%89glise_prieurale_de_Souvigny-Chapiteaux_%28c%29-20151026.jpg",
          "sourceUrl": "https://commons.wikimedia.org/wiki/File%3A%C3%89glise%20prieurale%20de%20Souvigny-Chapiteaux%20(c)-20151026.jpg",
          "title": "Église prieurale de Souvigny-Chapiteaux (c)-20151026.jpg",
          "description": "Capital of the Northern aisle.",
          "width": 5472,
          "height": 3648,
          "size": 9602841,
          "timestamp": "2015-11-01T06:27:34Z",
          "author": "Daniel VILLAFRUELA",
          "license": "CC BY-SA 4.0",
          "licenseUrl": "https://creativecommons.org/licenses/",
          "score": 6
        }
      ]
    },
    {
      "label": "Jardins du Prieuré",
      "photos": [
        {
          "url": "https://upload.wikimedia.org/wikipedia/commons/f/f6/Prieur%C3%A9_b%C3%A9n%C3%A9dictin_de_Souvigny-Vue_du_chemin_de_Saint_Jacques-20151026.jpg",
          "sourceUrl": "https://commons.wikimedia.org/wiki/File%3APrieur%C3%A9%20b%C3%A9n%C3%A9dictin%20de%20Souvigny-Vue%20du%20chemin%20de%20Saint%20Jacques-20151026.jpg",
          "title": "Prieuré bénédictin de Souvigny-Vue du chemin de Saint Jacques-20151026.jpg",
          "description": "View of the Priory St. Peter and St. Paul at the  exit of the Way of St. James, Aristide Briand square - (Waymarks near the fountain for pilgrims, far left).",
          "width": 5472,
          "height": 3648,
          "size": 7920319,
          "timestamp": "2015-10-29T08:47:56Z",
          "author": "Daniel VILLAFRUELA",
          "license": "CC BY-SA 4.0",
          "licenseUrl": "https://creativecommons.org/licenses/",
          "score": 8
        },
        {
          "url": "https://upload.wikimedia.org/wikipedia/commons/b/ba/Souvigny_%28www.xtof.photo%29.jpg",
          "sourceUrl": "https://commons.wikimedia.org/wiki/File%3ASouvigny%20(www.xtof.photo).jpg",
          "title": "Souvigny (www.xtof.photo).jpg",
          "description": "This is a panoramic view of Souvigny, including its medieval priory, the garden and the main square, from the sky.",
          "width": 2961,
          "height": 1440,
          "size": 1818796,
          "timestamp": "2019-08-15T16:18:23Z",
          "author": "Christophe Meneboeuf",
          "license": "CC BY-SA 4.0",
          "licenseUrl": "https://creativecommons.org/licenses/",
          "score": 8
        },
        {
          "url": "https://upload.wikimedia.org/wikipedia/commons/7/75/Prieurale_Saint-Pierre-et-Saint-Paul_de_Souvigny_-_Vue_depuis_le_jardin.jpg",
          "sourceUrl": "https://commons.wikimedia.org/wiki/File%3APrieurale%20Saint-Pierre-et-Saint-Paul%20de%20Souvigny%20-%20Vue%20depuis%20le%20jardin.jpg",
          "title": "Prieurale Saint-Pierre-et-Saint-Paul de Souvigny - Vue depuis le jardin.jpg",
          "description": "Prieurale Saint-Pierre-et-Saint-Paul de Souvigny - Vue depuis le jardin",
          "width": 3072,
          "height": 4080,
          "size": 3682682,
          "timestamp": "2024-11-09T07:23:55Z",
          "author": "Alexjes98",
          "license": "CC0",
          "licenseUrl": "https://creativecommons.org/licenses/",
          "score": 8
        }
      ]
    },
    {
      "label": "Musée de Souvigny",
      "photos": [
        {
          "url": "https://upload.wikimedia.org/wikipedia/commons/c/cb/Souvigny_-_M%C3%A9diath%C3%A8que_de_l%27architecture_et_du_patrimoine_-_APMH00035657.jpg",
          "sourceUrl": "https://commons.wikimedia.org/wiki/File%3ASouvigny%20-%20M%C3%A9diath%C3%A8que%20de%20l'architecture%20et%20du%20patrimoine%20-%20APMH00035657.jpg",
          "title": "Souvigny - Médiathèque de l'architecture et du patrimoine - APMH00035657.jpg",
          "description": "",
          "width": 725,
          "height": 512,
          "size": 74593,
          "timestamp": "2020-04-27T10:31:52Z",
          "author": "<bdi><a href=\"https://en.wikipedia.org/wiki/en:Camille_Enlart\" class=\"extiw\" title=\"w:en:Camille Enlart\"><span title=\"French art historian and photographer (1862-1927)\">Camille Enlart</span></a></bdi>",
          "license": "CC BY-SA 4.0",
          "licenseUrl": "https://creativecommons.org/licenses/",
          "score": 4
        }
      ]
    }
  ]
}